Metadata-Version: 2.1
Name: odoo8-addon-base-external-dbsource
Version: 8.0.1.3.0.99.dev35
Summary: External Database Sources
Home-page: http://launchpad.net/addons-tko
Author: Daniel Reis,Odoo Community Association (OCA)
Author-email: support@odoo-community.org
License: AGPL-3
Platform: UNKNOWN
Classifier: Programming Language :: Python
Classifier: Framework :: Odoo
Classifier: Framework :: Odoo :: 8.0
Classifier: License :: OSI Approved :: GNU Affero General Public License v3
Requires-Python: ~=2.7
Requires-Dist: odoo (<9.0a,>=8.0a)
